ALU.v
module alu (
input [7:0] A,
	input [7:0] B,
	input [2:0] opcode,
	output reg [7:0] result,
	output reg carry,
    output reg zero
);
always @(*) begin
    carry = 0;
    case (opcode)
        3'b000: {carry, result} = A + B;        // ADD
        3'b001: {carry, result} = A - B;        // SUB
        3'b010: result = A & B;                 // AND
        3'b011: result = A | B;                 // OR
        3'b100: result = A ^ B;                 // XOR
        3'b101: result = ~A;                    // NOT
        3'b110: result = A << 1;                // LSHIFT
        3'b111: result = A >> 1;                // RSHIFT
        default: result = 8'b0;
    endcase
    zero = (result == 0);
end
endmodule

ALU_tb.v
module alu_tb;
reg [7:0] A, B;
reg [2:0] opcode;
wire [7:0] result;
wire carry, zero;

alu uut (
    .A(A),
    .B(B),
    .opcode(opcode),
    .result(result),
    .carry(carry),
    .zero(zero)
);

initial begin
    $dumpfile("alu.vcd");
    $dumpvars(0, alu_tb);

    A = 8'd10; B = 8'd5;
    opcode = 3'b000; #10;  // ADD
    opcode = 3'b001; #10;  // SUB
    opcode = 3'b010; #10;  // AND
    opcode = 3'b011; #10;  // OR
    opcode = 3'b100; #10;  // XOR
    opcode = 3'b101; #10;  // NOT
    opcode = 3'b110; #10;  // LSHIFT
    opcode = 3'b111; #10;  // RSHIFT
    $finish;
end
endmodule

alu.vcd
$date
	Sun Feb 15 12:42:25 2026
$end
$version
	Icarus Verilog
$end
$timescale
	1s
$end
$scope module alu_tb $end
$var wire 1 ! zero $end
$var wire 8 " result [7:0] $end
$var wire 1 # carry $end
$var reg 8 $ A [7:0] $end
$var reg 8 % B [7:0] $end
$var reg 3 & opcode [2:0] $end
$scope module uut $end
$var wire 8 ' A [7:0] $end
$var wire 8 ( B [7:0] $end
$var wire 3 ) opcode [2:0] $end
$var reg 1 # carry $end
$var reg 8 * result [7:0] $end
$var reg 1 ! zero $end
$upscope $end
$upscope $end
$enddefinitions $end
#0
$dumpvars
b1111 *
b0 )
b101 (
b1010 '
b0 &
b101 %
b1010 $
0#
b1111 "
0!
$end
#10
b101 "
b101 *
b1 &
b1 )
#20
1!
b0 "
b0 *
b10 &
b10 )
#30
0!
b1111 "
b1111 *
b11 &
b11 )
#40
b100 &
b100 )
#50
b11110101 "
b11110101 *
b101 &
b101 )
#60
b10100 "
b10100 *
b110 &
b110 )
#70
b101 "
b101 *
b111 &
b111 )
